{
  "id": "task-20260326-164652-a3326f2e",
  "title": "Check ingestion pipeline status",
  "agent_id": "a3326f2e11c5f7ef6",
  "agent_type": "general-purpose",
  "session_id": "ef1a5e01-b3c3-41d6-abd3-172f68d92559",
  "discord_message_id": null,
  "discord_user": null,
  "run_in_background": true,
  "isolation": null,
  "model": null,
  "log": [
    {
      "ts": "2026-03-26T16:46:52Z",
      "event": "started",
      "context": "Check ingestion pipeline status"
    },
    {
      "ts": "2026-03-26T16:48:04Z",
      "event": "done",
      "context": "Here's the full status report:\n\n**scrape_discord_worker.py process:** Not running. The process has completed (or died) — no active PID for it.\n\n**Log file (`/tmp/discord-ingest-bootstrap3.log`):**\n- Last modified: 16:47:34 UTC (about 1 second before current time when I checked ~16:47)\n- The ingestion was actively working and made it through 3/11 episodes:\n  - `[1/11]` Centronias (818 msgs) — ingested at 16:43:52\n  - `[2/11]` BigClungus (2250 msgs) — ingested at 16:45:20\n  - `[3/11]` Jaboostin (6...(truncated)",
      "artifacts": []
    }
  ]
}
