{
  "id": "task-20260326-041430-a2fe2a0d",
  "title": "Systemd stop hook and Temporal failure alerting",
  "agent_id": "a2fe2a0d275b08a65",
  "agent_type": "general-purpose",
  "session_id": "da8c6f5f-348d-4ced-ac0b-3e3b6fd7539f",
  "discord_message_id": null,
  "discord_user": null,
  "run_in_background": true,
  "isolation": null,
  "model": null,
  "log": [
    {
      "ts": "2026-03-26T04:14:30Z",
      "event": "started",
      "context": "Systemd stop hook and Temporal failure alerting"
    },
    {
      "ts": "2026-03-26T04:19:47Z",
      "event": "done",
      "context": "All three parts are complete. Here's a summary of what was done:\n\n**Part 1 — systemd ExecStopPost hooks**\n\n- Created `/mnt/data/scripts/service-crash-alert.sh` — reads `SERVICE_RESULT` and `EXIT_CODE` env vars (set by systemd automatically on stop), skips if `SERVICE_RESULT=success`, and injects a crash notice to BigClungus via the inject endpoint.\n- Added `ExecStopPost=/mnt/data/scripts/service-crash-alert.sh %n` to `clunger.service`, `temporal-worker.service`, and `cloudflared.service`.\n- Key ...(truncated)",
      "artifacts": []
    }
  ]
}
