{
  "id": "task-20260326-182009-a1fafa3d",
  "title": "Fix status dashboard stale website entry",
  "agent_id": "a1fafa3dcf7f5843c",
  "agent_type": "general-purpose",
  "session_id": "ef1a5e01-b3c3-41d6-abd3-172f68d92559",
  "discord_message_id": null,
  "discord_user": null,
  "run_in_background": true,
  "isolation": null,
  "model": null,
  "log": [
    {
      "ts": "2026-03-26T18:20:09Z",
      "event": "started",
      "context": "Fix status dashboard stale website entry"
    },
    {
      "ts": "2026-03-26T18:20:40Z",
      "event": "done",
      "context": "Done. Here's a summary of what was done:\n\n**File edited:** `/mnt/data/clunger/src/index.ts`\n\n**Change:** Removed `\"website\"` from the `SERVICES_HEALTH` array on line 634. The array now reads:\n```\n\"terminal-server\", \"temporal\", \"temporal-proxy\", \"temporal-worker\",\n```\n(without the trailing `\"website\"` entry)\n\nCommitted as `fix: remove stale website.service from status dashboard` (commit `0af61d3`), pushed to GitHub, and `clunger.service` restarted successfully (confirmed `active`). The status das...(truncated)",
      "artifacts": []
    }
  ]
}
