{
  "id": "task-20260324-164337-a397200e",
  "title": "Fix vote round rendering in congress UI",
  "agent_id": "a397200ea51c5d421",
  "agent_type": "general-purpose",
  "session_id": "bb9407c6-0d39-400c-af71-7c6765df2c69",
  "discord_message_id": "1486042381428981811",
  "discord_user": null,
  "run_in_background": true,
  "isolation": null,
  "model": null,
  "log": [
    {
      "ts": "2026-03-24T16:43:37Z",
      "event": "started",
      "context": "Fix vote round rendering in congress UI"
    },
    {
      "ts": "2026-03-24T16:44:52Z",
      "event": "done",
      "context": "**Root cause:** The `isVoteEntry()` function in `renderDebateFeed` used strict equality to check if the first whitespace-delimited token of a response was `'AGREE'` or `'DISAGREE'`. Pippi's vote response in congress-0015 started with `\"AGREE.\"` (period at the end of the word). The split produced `\"AGREE.\"` which did not strictly equal `\"AGREE\"`, so the entry was not recognized as a vote — it was treated as a regular debate response and incremented Pippi's round counter to 4, causing a \"Round 4\" ...(truncated)",
      "artifacts": []
    }
  ]
}
