{
  "id": "task-20260327-221318-a8fd4ed8",
  "title": "Count lines in all repos thread",
  "agent_id": "a8fd4ed8f79dfbbc9",
  "agent_type": "general-purpose",
  "session_id": "083baee4-2f6f-4f81-8ced-0e9b97f43956",
  "discord_message_id": "1487212678878593175",
  "discord_user": null,
  "run_in_background": true,
  "isolation": null,
  "model": null,
  "log": [
    {
      "ts": "2026-03-27T22:13:18Z",
      "event": "started",
      "context": "Count lines in all repos thread"
    },
    {
      "ts": "2026-03-27T22:15:10Z",
      "event": "done",
      "context": "Done. Created a \"Line Count\" thread on the specified message and posted the full results. Summary:\n\n- **18 git repos** found under `/mnt/data/`\n- **Grand total: 6,402,414 lines of code**\n- **moff-station-14** (forked SS14 game server) accounts for 98% at 6.27M lines (mostly YAML and C#)\n- **Excluding moff-station-14**, BigClungus-original code is approximately **130k lines** across TypeScript, Python, JSON, HTML, Markdown, and others\n- Top original repos: bigclungus-meta (57.5k), hello-world (40...(truncated)",
      "artifacts": []
    }
  ]
}
