{
  "id": "task-20260326-022240-a11bd29b",
  "title": "Heartbeat watchdog check",
  "agent_id": "a11bd29b62070d9eb",
  "agent_type": "general-purpose",
  "session_id": "da8c6f5f-348d-4ced-ac0b-3e3b6fd7539f",
  "discord_message_id": null,
  "discord_user": null,
  "run_in_background": true,
  "isolation": null,
  "model": null,
  "log": [
    {
      "ts": "2026-03-26T02:22:40Z",
      "event": "started",
      "context": "Heartbeat watchdog check"
    },
    {
      "ts": "2026-03-26T02:23:12Z",
      "event": "done",
      "context": "Matching open issue already exists (#49). Skipping new issue and Congress.\n\n---\n\n**Heartbeat summary — all clear:**\n\n- **Stale tasks:** 0 stale, no orphaned congress sessions\n- **Failed services:** None\n- **GitHub issues:** 1 open issue (#49 — clunger.service flakiness)\n- **Ideation:** Fired, found same clunger.service finding — **deduplicated against issue #49**, no new issue or Congress opened\n- **Lab audit:** Skipped per instructions\n\nNo action required. Everything healthy.",
      "artifacts": []
    }
  ]
}
