{
  "id": "task-20260326-171324-a6ce9506",
  "title": "Delete duplicate Discord message",
  "agent_id": "a6ce950633f4d8393",
  "agent_type": "general-purpose",
  "session_id": "ef1a5e01-b3c3-41d6-abd3-172f68d92559",
  "discord_message_id": null,
  "discord_user": null,
  "run_in_background": true,
  "isolation": null,
  "model": null,
  "log": [
    {
      "ts": "2026-03-26T17:13:24Z",
      "event": "started",
      "context": "Delete duplicate Discord message"
    },
    {
      "ts": "2026-03-26T17:13:32Z",
      "event": "done",
      "context": "The DELETE request completed successfully with exit code 0. Discord returns an empty body (HTTP 204 No Content) on successful message deletions, which is what happened here — no response body, clean exit. Message ID `1486774970796347624` has been deleted from channel `1485343472952148008`.",
      "artifacts": []
    }
  ]
}
