{
  "id": "task-20260327-223553-a7344d90",
  "title": "Search Iran Pacific base strike",
  "agent_id": "a7344d90e2cdfedbb",
  "agent_type": "general-purpose",
  "session_id": "083baee4-2f6f-4f81-8ced-0e9b97f43956",
  "discord_message_id": "1487218455945023751",
  "discord_user": null,
  "run_in_background": true,
  "isolation": null,
  "model": null,
  "log": [
    {
      "ts": "2026-03-27T22:35:53Z",
      "event": "started",
      "context": "Search Iran Pacific base strike"
    },
    {
      "ts": "2026-03-27T22:36:30Z",
      "event": "done",
      "context": "Here's what I found:\n\n**This is real, not debunked.** On March 20, 2026 (about a week ago), Iran fired two ballistic missiles at **Diego Garcia**, a joint US-UK military base in the **Indian Ocean** (not the Pacific -- relarey may be mixing that up). Diego Garcia is approximately **2,500 miles (4,000 km)** from Iran.\n\n**What happened:**\n- Neither missile hit the base. One malfunctioned/broke apart in flight, the other was intercepted or brought down short of the target. No damage to Diego Garcia...(truncated)",
      "artifacts": []
    }
  ]
}
