{
  "id": "task-20260325-155959-a751d17b",
  "title": "Finalize migration plan with project name and parallel dev",
  "agent_id": "a751d17ba468ae268",
  "agent_type": "general-purpose",
  "session_id": "4a58e62d-fa69-4ca2-a0a8-edcc21bb73c1",
  "discord_message_id": "1486393772144328725",
  "discord_user": null,
  "run_in_background": true,
  "isolation": null,
  "model": null,
  "log": [
    {
      "ts": "2026-03-25T15:59:59Z",
      "event": "started",
      "context": "Finalize migration plan with project name and parallel dev"
    },
    {
      "ts": "2026-03-25T16:00:29Z",
      "event": "done",
      "context": "Done. Changes made to `/mnt/data/bigclungus-meta/plans/serve-py-to-ts-proto-migration.md`:\n\n1. **Renamed `hello-world-ts/` to `clunger/`** — one occurrence in Phase 2 of the work breakdown (\"Create `clunger/` project with Bun\").\n\n2. **Added \"Parallel Development Approach\" section** before \"Open Questions\" — covers the concurrent dev setup (port 8081 for clunger, :8080 stays as serve.py), the new `clunger.service` systemd unit, the diff-based verification approach, and the Cloudflare route-swap c...(truncated)",
      "artifacts": []
    }
  ]
}
