{
  "id": "task-20260330-200209-a5a4018b",
  "title": "Fetch centronias image for advice",
  "agent_id": "a5a4018b86aec4f4c",
  "agent_type": "general-purpose",
  "session_id": "cd5c6ab2-9176-47d3-b93e-4e96320e5feb",
  "discord_message_id": null,
  "discord_user": null,
  "run_in_background": true,
  "isolation": null,
  "model": null,
  "log": [
    {
      "ts": "2026-03-30T20:02:08Z",
      "event": "started",
      "context": "Fetch centronias image for advice"
    },
    {
      "ts": "2026-03-30T20:02:23Z",
      "event": "done",
      "context": "The image is a comic panel showing a character (looks like the \"troll face\" / meme-style round-headed character) in a blue shirt and orange tie, with a speech bubble saying \"BURGERS?\"\n\nThis is a classic \"Burgers?\" meme — typically used to derail a serious conversation or to suggest getting food instead of dealing with whatever's going on. It's a humorous non-sequitur deflection.\n\n**Advice to give centronias:** The meme is asking if you want burgers. The correct answer is yes. Always yes to burge...(truncated)",
      "artifacts": []
    }
  ]
}
