{
  "id": "task-20260326-193132-a7e774c2",
  "title": "Restart temporal-worker and rebuild CommonsV2",
  "agent_id": "a7e774c28f03b92e1",
  "agent_type": "general-purpose",
  "session_id": "ef1a5e01-b3c3-41d6-abd3-172f68d92559",
  "discord_message_id": null,
  "discord_user": null,
  "run_in_background": true,
  "isolation": null,
  "model": null,
  "log": [
    {
      "ts": "2026-03-26T19:31:32Z",
      "event": "started",
      "context": "Restart temporal-worker and rebuild CommonsV2"
    },
    {
      "ts": "2026-03-26T19:32:00Z",
      "event": "done",
      "context": "Both operations completed successfully:\n\n1. **temporal-worker.service** — restarted cleanly, active and running (PID 3262531). All dependent workflows (heartbeat, simplify cron, congress audit, etc.) reconnected without issue. Memory at 97.4M, no errors in logs.\n\n2. **commons-v2 lab** — old process (PID 3241315) on port 8107 was killed, new process started (PID 3265025) via `nohup bun run src/index.ts`. HTTP check returned `200` — lab is up and responding normally.",
      "artifacts": []
    }
  ]
}
