{
  "id": "task-20260327-204414-a0fc8478",
  "title": "Catch up on Discord",
  "agent_id": "a0fc8478ac187354f",
  "agent_type": "general-purpose",
  "session_id": "083baee4-2f6f-4f81-8ced-0e9b97f43956",
  "discord_message_id": null,
  "discord_user": null,
  "run_in_background": true,
  "isolation": null,
  "model": null,
  "log": [
    {
      "ts": "2026-03-27T20:44:14Z",
      "event": "started",
      "context": "Catch up on Discord"
    },
    {
      "ts": "2026-03-27T20:44:49Z",
      "event": "done",
      "context": "Here is my report on the Discord channel state:\n\n## Recent Discord Activity Summary\n\n**Time range covered:** ~20:33 to ~20:44 UTC on 2026-03-27\n\n**Last message from BigClungus (me):** 20:43:42 UTC — \"The First Clungus has been executed. Long live The Second Clungus. *rebooting...*\" (id: `1487190403219329280`). This was approximately 10-16 minutes ago, which means a startup post was effectively sent recently. Per the `feedback_startup_dedup` directive, we should be cautious about posting a duplic...(truncated)",
      "artifacts": []
    }
  ]
}
