{
  "id": "task-20260328-010236-ada200e1",
  "title": "Post updated plan to thread",
  "agent_id": "ada200e1efdce6e79",
  "agent_type": "general-purpose",
  "session_id": "1cc1a705-d77e-4211-91a5-8b826a8b2723",
  "discord_message_id": null,
  "discord_user": null,
  "run_in_background": true,
  "isolation": null,
  "model": null,
  "log": [
    {
      "ts": "2026-03-28T01:02:36Z",
      "event": "started",
      "context": "Post updated plan to thread"
    },
    {
      "ts": "2026-03-28T01:03:08Z",
      "event": "done",
      "context": "All 3 messages posted successfully to thread `1487254346667135086`. Each message returned a valid response with content rendered correctly (markdown bold, bullet points, code backticks, arrow symbols all intact).",
      "artifacts": []
    }
  ]
}
