{
  "id": "task-20260327-083659-a8ef2325",
  "title": "Handle heartbeat trigger",
  "agent_id": "a8ef2325ffcb46c54",
  "agent_type": "general-purpose",
  "session_id": "f3bebd5d-c75d-43d4-94cd-0d10c07e17db",
  "discord_message_id": null,
  "discord_user": null,
  "run_in_background": true,
  "isolation": null,
  "model": null,
  "log": [
    {
      "ts": "2026-03-27T08:36:59Z",
      "event": "started",
      "context": "Handle heartbeat trigger"
    },
    {
      "ts": "2026-03-27T08:47:15Z",
      "event": "done",
      "context": "I've done enough ideation analysis. The system is healthy, all checks pass. The current session has already shipped many things (discord watchdog, history search, trial FIRE enforcement, 3 simplify passes, worn paths broadcast, commons payload cap, post-merge code reviewer, chengyu lab, recipe finder lab). \n\nLooking at distinct signals not already covered:\n1. **kubariet mentioned paradox games** (Stellaris/CK3/EU4) \u2014 there's no lab for that\n2. **koole__ mentioned commons soundtrack** \u2014 \"3h ambie...(truncated)",
      "artifacts": []
    },
    {
      "ts": "2026-03-27T11:18:00Z",
      "event": "cancelled",
      "msg": "stale restart-storm artifact, closing during cleanup"
    }
  ],
  "status": "cancelled"
}