{
  "id": "task-20260328-194248-ae42a148",
  "title": "Thread: Commons RPG expansion plan",
  "agent_id": "ae42a1487560c6edf",
  "agent_type": "general-purpose",
  "session_id": "5aac769e-2e6e-4bd3-a873-645eb001e989",
  "discord_message_id": null,
  "discord_user": null,
  "run_in_background": true,
  "isolation": null,
  "model": null,
  "log": [
    {
      "ts": "2026-03-28T19:42:48Z",
      "event": "started",
      "context": "Thread: Commons RPG expansion plan"
    },
    {
      "ts": "2026-03-28T19:44:11Z",
      "event": "done",
      "context": "Done. Created the \"Commons RPG Expansion\" thread on jaboostin's message and posted a two-part response covering:\n\n1. **Current state assessment** — what Commons already has (multiplayer WS, tile world, NPC AI, OAuth)\n2. **5-phase expansion plan:**\n   - Phase 1: Character creation, classes (Fighter/Mage/Ranger/Diplomat), stats, inventory, SQLite persistence\n   - Phase 2: Hub town redesign — Congress building as \"The Senate\" with buff mechanics, persona NPCs as shopkeepers\n   - Phase 3: Procedural...(truncated)",
      "artifacts": []
    }
  ]
}
